{"quality":3.8,"latitude":41.7225,"version":"eabfa710a2d0b0a63e7ccb1be4826ade5ffa28a09e73d919c8ec60e76aa628dd","shuttleSeconds":null,"riskRating":null,"timeRating":"II","vehicle":null,"rappelCountMax":null,"rappelLongestMeters":50,"name":"Arado","permit":"No","technicalRating":4,"rappelCountMin":null,"longitude":-8.1297,"waterRating":"C","description":"<div class=\"mw-content-ltr mw-parser-output\" lang=\"en\" dir=\"ltr\"><meta property=\"mw:PageProp\/toc\" \/>\n<div class=\"mw-heading mw-heading2\"><h2 id=\"Approach\">Approach<\/h2><\/div>\n<div class=\"mw-heading mw-heading2\"><h2 id=\"Descent\">Descent<\/h2><\/div>\n<div class=\"mw-heading mw-heading2\"><h2 id=\"Exit\">Exit<\/h2><\/div>\n<div class=\"mw-heading mw-heading2\"><h2 id=\"Red_tape\">Red tape<\/h2><\/div>\n<div class=\"mw-heading mw-heading2\"><h2 id=\"Beta_sites\">Beta sites<\/h2><\/div>\n<ul><li><a rel=\"nofollow\" class=\"external text\" href=\"http:\/\/descente-canyon.com\/canyoning\/canyon-description\/21210\">Descente-Canyon.com<\/a> &#160;: Arado<\/li>\n<li><a rel=\"nofollow\" class=\"external text\" href=\"http:\/\/canyon.carto.net\/cwiki\/bin\/view\/Canyons\/AradoCanyon\">Canyon.Carto.net<\/a> &#160;: Barranco del Arado superior<\/li>\n<li><a rel=\"nofollow\" class=\"external text\" href=\"http:\/\/canyoning.wroclaw.pl\/kanion.php?id=99\">Canyoning.Wroclaw.pl<\/a> &#160;: Arado<\/li>\n<li><a rel=\"nofollow\" class=\"external text\" href=\"http:\/\/media.wix.com\/ugd\/7acf9c_5725b8f639c3459f99b79fcdfed6df9d.pdf\">ECDCPortugal.com<\/a> &#160;: Rio Arado Sup.<\/li>\n<li><a rel=\"nofollow\" class=\"external text\" href=\"http:\/\/media.wix.com\/ugd\/7acf9c_c09312eed53a45e3be3467da24a396b5.pdf\">ECDCPortugal.com<\/a> &#160;: Rio Arado Inf.<\/li>\n<li><a rel=\"nofollow\" class=\"external text\" href=\"https:\/\/www.docuwiki.infobarrancos.es\/doku.php?id=portugal:braga:arado_sup\">Wiki-Infobarrancos<\/a>&#160;: Canyon Rio Arado Superior (<a rel=\"nofollow\" class=\"external free\" href=\"http:\/\/infobarrancos.es\/\">http:\/\/infobarrancos.es\/<\/a>)<\/li><\/ul>\n<div class=\"mw-heading mw-heading2\"><h2 id=\"Trip_reports_and_media\">Trip reports and media<\/h2><\/div>\n<ul><li><a rel=\"nofollow\" class=\"external text\" href=\"http:\/\/WWW.barranquistas.es\/2008\/03\/despus-de-dos-meses-inactivo-al-fin.html\">Barranquistas.es<\/a> &#160;: CAÑONES DE PORTUGAL: ARADO Y FAFIÄO<\/li>\n<li><a rel=\"nofollow\" class=\"external text\" href=\"http:\/\/wikiloc.com\/wikiloc\/view.do?id=2020156\">Wikiloc.com<\/a> &#160;: Barranco del Arado; en Braga (Portugal)<\/li>\n<li><a rel=\"nofollow\" class=\"external text\" href=\"http:\/\/wikiloc.com\/wikiloc\/view.do?id=9205902\">Wikiloc.com<\/a> &#160;: Canyoning Rio Arado<\/li>\n<li><a rel=\"nofollow\" class=\"external text\" href=\"http:\/\/wikiloc.com\/wikiloc\/view.do?id=1909178\">Wikiloc.com<\/a> &#160;: fafiao arado<\/li><\/ul>\n<div class=\"mw-heading mw-heading2\"><h2 id=\"Background\">Background<\/h2><\/div>\n\n\n<\/div>","id":16038,"geojson":{"features":[{"geometry":{"type":"Point","coordinates":[[-8.130907,41.734699,0]]},"type":"Feature","properties":{"name":"Start"}},{"type":"Feature","geometry":{"coordinates":[[-8.129668,41.722996,0]],"type":"Point"},"properties":{"name":"End"}},{"geometry":{"type":"Point","coordinates":[[-8.12966,41.722534,0]]},"properties":{"name":"Parking"},"type":"Feature"},{"geometry":{"type":"Point","coordinates":[[-8.158422,41.735134,0]]},"properties":{"name":"Waypoint Approach\/Exit"},"type":"Feature"}],"type":"FeatureCollection"},"months":["May","Jun","Jul","Aug","Sep","Oct"],"url":"https:\/\/ropewiki.com\/Arado"}