{
  "url": "https://ropewiki.com/Eichorn_Pinnacle",
  "latitude": 37.8476,
  "longitude": -119.4071,
  "id": 20155,
  "name": "Eichorn Pinnacle",
  "quality": 4.8,
  "months": [
    "Jul",
    "Aug",
    "Sep",
    "Oct"
  ],
  "technicalRating": 3,
  "waterRating": "A",
  "timeRating": "III",
  "permit": "No",
  "description": "<h2 id=\"introduction\">Introduction</h2>\n<h2 id=\"approach\">Approach</h2>\n<h2 id=\"descent\">Descent</h2>\n<h2 id=\"exit\">Exit</h2>\n<h2 id=\"red_tape\">Red tape</h2>\n<h2 id=\"beta_sites\">Beta sites</h2>\n<ul>\n<li><img src=\"rwl_en.png\" title=\"rwl_en.png\" alt=\"rwl_en.png\" /><a\nhref=\"http://brennen.caltech.edu/swhikes/eichrn.htm\">Chris Brennen's\nAdventure Hikes (Southwest)</a> : Eichorn Pinnacle</li>\n</ul>\n<h2 id=\"trip_reports_and_media\">Trip reports and media</h2>\n<h2 id=\"background\">Background</h2>\n",
  "geojson": {
    "type": "FeatureCollection",
    "features": [
      {
        "type": "Feature",
        "geometry": {
          "type": "Point",
          "coordinates": [
            -119.382835,
            37.873333,
            0
          ]
        },
        "properties": {
          "name": "Wpt1",
          "styleUrl": "#dot",
          "styleHash": "-56beb8bb",
          "styleMapHash": {
            "normal": "#dot0",
            "highlight": "#dot1"
          },
          "icon": "http://maps.google.com/mapfiles/kml/shapes/open-diamond.png",
          "description": "Hike The approach begins at the Cathedral Lakes trailhead (Data by brennen.caltech.edu/swhikes)"
        }
      },
      {
        "type": "Feature",
        "geometry": {
          "type": "Point",
          "coordinates": [
            -119.388496,
            37.8685,
            0
          ]
        },
        "properties": {
          "name": "Wpt2",
          "styleUrl": "#dot",
          "styleHash": "-56beb8bb",
          "styleMapHash": {
            "normal": "#dot0",
            "highlight": "#dot1"
          },
          "icon": "http://maps.google.com/mapfiles/kml/shapes/open-diamond.png",
          "description": "Follow the Cathedral Lakes trail for about half a mile to where a fairly well-used use-trail forks off to the left (about (Data by brennen.caltech.edu/swhikes)"
        }
      }
    ]
  }
}