{
  "url": "https://ropewiki.com/Wolfskill_Canyon",
  "latitude": 34.1722,
  "longitude": -117.7195,
  "id": 441,
  "name": "Wolfskill Canyon",
  "quality": 3,
  "technicalRating": 3,
  "waterRating": "B",
  "timeRating": "III",
  "permit": "No",
  "rappelCountMin": 3,
  "rappelCountMax": 3,
  "rappelLongestMeters": 33.53,
  "vehicle": "Passenger",
  "description": "<h2 id=\"introduction\">Introduction</h2>\n<h2 id=\"approach\">Approach</h2>\n<h2 id=\"descent\">Descent</h2>\n<h2 id=\"exit\">Exit</h2>\n<h2 id=\"red_tape\">Red tape</h2>\n<h2 id=\"beta_sites\">Beta sites</h2>\n<ul>\n<li><img src=\"rwl_en.png\" title=\"rwl_en.png\" alt=\"rwl_en.png\" /><a\nhref=\"http://brennen.caltech.edu/advents/wolfsk.htm\">Chris Brennen's\nAdventure Hikes (St Gabriels)</a> : Wolfskill Canyon</li>\n<li><img src=\"rwl_en.png\" title=\"rwl_en.png\" alt=\"rwl_en.png\" /><a\nhref=\"http://ropewiki.com/User:Super_Amazing_Map?id=Wolfskill_Canyon_-_California_(San_Gabriels)\">Super\nAmazing Map</a> : Wolfskill Canyon</li>\n</ul>\n<h2 id=\"trip_reports_and_media\">Trip reports and media</h2>\n<h2 id=\"background\">Background</h2>\n",
  "geojson": {
    "type": "FeatureCollection",
    "features": [
      {
        "type": "Feature",
        "geometry": {
          "type": "Point",
          "coordinates": [
            -117.750504,
            34.165165,
            0
          ]
        },
        "properties": {
          "name": "Wpt1",
          "styleUrl": "#dot",
          "styleHash": "-56beb8bb",
          "styleMapHash": {
            "normal": "#dot0",
            "highlight": "#dot1"
          },
          "icon": "http://maps.google.com/mapfiles/kml/shapes/open-diamond.png",
          "description": "Though steep it is broad and easy to follow and you should reach the road (at (Data by brennen.caltech.edu/advents)"
        }
      },
      {
        "type": "Feature",
        "geometry": {
          "type": "Point",
          "coordinates": [
            -117.71833,
            34.169998,
            0
          ]
        },
        "properties": {
          "name": "Wpt2",
          "styleUrl": "#dot",
          "styleHash": "-56beb8bb",
          "styleMapHash": {
            "normal": "#dot0",
            "highlight": "#dot1"
          },
          "icon": "http://maps.google.com/mapfiles/kml/shapes/open-diamond.png",
          "description": "This is the drop in point at (Data by brennen.caltech.edu/advents)"
        }
      },
      {
        "type": "Feature",
        "geometry": {
          "type": "Point",
          "coordinates": [
            -117.719498,
            34.172165,
            0
          ]
        },
        "properties": {
          "name": "Wpt3",
          "styleUrl": "#dot",
          "styleHash": "-56beb8bb",
          "styleMapHash": {
            "normal": "#dot0",
            "highlight": "#dot1"
          },
          "icon": "http://maps.google.com/mapfiles/kml/shapes/open-diamond.png",
          "description": "Following the gully and descending about 450ft you will arrive in the bottom of Wolfskill Canyon (Data by brennen.caltech.edu/advents)"
        }
      },
      {
        "type": "Feature",
        "geometry": {
          "type": "Point",
          "coordinates": [
            -117.768501,
            34.166332,
            0
          ]
        },
        "properties": {
          "name": "Wpt4",
          "styleUrl": "#dot",
          "styleHash": "-56beb8bb",
          "styleMapHash": {
            "normal": "#dot0",
            "highlight": "#dot1"
          },
          "icon": "http://maps.google.com/mapfiles/kml/shapes/open-diamond.png",
          "description": "Finally 2mi and 45min below Wolfskill Falls you come to the San Dimas Canyon entrance gate (Data by brennen.caltech.edu/advents)"
        }
      }
    ]
  }
}