{"name":"Caminito del Rey","permit":"Yes","url":"https:\/\/ropewiki.com\/Caminito_del_Rey","geojson":null,"latitude":36.933,"quality":3,"rappelLongestMeters":null,"version":"364d474ef41bc6cc7ba5e494710b1686280ffea5bd865a51caceb16ead9a2160","timeRating":"II","longitude":-4.8029,"rappelCountMax":null,"waterRating":"A","technicalRating":1,"id":51839,"months":["Jan","Feb","Mar","Apr","May","Jun","Jul","Aug","Sep","Oct","Nov","Dec"],"shuttleSeconds":1800,"riskRating":null,"rappelCountMin":null,"description":"<div class=\"mw-content-ltr mw-parser-output\" lang=\"en\" dir=\"ltr\"><p>Used to be more of a via ferrata, now it is very tame and an easy hike\n<\/p>\n<meta property=\"mw:PageProp\/toc\" \/>\n<div class=\"mw-heading mw-heading2\"><h2 id=\"Approach\">Approach<\/h2><\/div>\n<div class=\"mw-heading mw-heading2\"><h2 id=\"Descent\">Descent<\/h2><\/div>\n<div class=\"mw-heading mw-heading2\"><h2 id=\"Exit\">Exit<\/h2><\/div>\n<div class=\"mw-heading mw-heading2\"><h2 id=\"Red_tape\">Red tape<\/h2><\/div>\n<div class=\"mw-heading mw-heading2\"><h2 id=\"Beta_sites\">Beta sites<\/h2><\/div>\n<div class=\"mw-heading mw-heading2\"><h2 id=\"Trip_reports_and_media\">Trip reports and media<\/h2><\/div>\n<div class=\"mw-heading mw-heading2\"><h2 id=\"Background\">Background<\/h2><\/div>\n<!-- \nNewPP limit report\nParsed by mw‐api‐ext.codfw.main‐6779cc57fc‐m54fq\nCached time: 20240914192016\nCache expiry: 2592000\nReduced expiry: false\nComplications: [show‐toc]\nCPU time usage: 0.004 seconds\nReal time usage: 0.005 seconds\nPreprocessor visited node count: 21\/1000000\nPost‐expand include size: 0\/2097152 bytes\nTemplate argument size: 0\/2097152 bytes\nHighest expansion depth: 2\/100\nExpensive parser function count: 0\/500\nUnstrip recursion depth: 0\/20\nUnstrip post‐expand size: 0\/5000000 bytes\nNumber of Wikibase entities loaded: 0\/400\n-->\n<!--\nTransclusion expansion time report (%,ms,calls,template)\n100.00%    0.000      1 -total\n-->\n<\/div>","vehicle":"Passenger"}